astroplan/__init__.py
astroplan/_astropy_init.py
astroplan/conftest.py
astroplan/constraints.py
astroplan/exceptions.py
astroplan/moon.py
astroplan/observer.py
astroplan/periodic.py
astroplan/scheduling.py
astroplan/setup_package.py
astroplan/target.py
astroplan/utils.py
astroplan/version.py
astroplan/plots/__init__.py
astroplan/plots/finder.py
astroplan/plots/mplstyles.py
astroplan/plots/sky.py
astroplan/plots/time_dependent.py
astroplan/plots/tests/__init__.py
astroplan/plots/tests/test_sky.py
astroplan/plots/tests/baseline_images/test_image_example.png
astroplan/tests/__init__.py
astroplan/tests/coveragerc
astroplan/tests/test_constraints.py
astroplan/tests/test_moon.py
astroplan/tests/test_observer.py
astroplan/tests/test_periodic.py
astroplan/tests/test_scheduling.py
astroplan/tests/test_target.py
astroplan/tests/test_utils.py
astroplan-0.6.dist-info/LICENSE.rst
astroplan-0.6.dist-info/METADATA
astroplan-0.6.dist-info/WHEEL
astroplan-0.6.dist-info/entry_points.txt
astroplan-0.6.dist-info/top_level.txt
astroplan-0.6.dist-info/RECORD
