Metadata-Version: 2.1
Name: astroplan
Version: 0.6
Summary: Observation planning package for astronomers
Home-page: https://github.com/astropy/astroplan
Author: Astroplan developers
Author-email: astropy-dev@googlegroups.com
License: BSD
Platform: UNKNOWN
Classifier: Development Status :: 1 - Planning
Classifier: Intended Audience :: Science/Research
Classifier: Topic :: Scientific/Engineering :: Astronomy
Classifier: License :: OSI Approved :: BSD License
Classifier: Operating System :: OS Independent
Classifier: Programming Language :: Python :: 3
Classifier: Programming Language :: Python :: 3.3
Classifier: Programming Language :: Python :: 3.4
Provides: astroplan
Provides-Extra: plotting
Provides-Extra: docs
Provides-Extra: test
